.DS_Store
beancount_fava-1.2.1.dist-info/DESCRIPTION.rst
beancount_fava-1.2.1.dist-info/METADATA
beancount_fava-1.2.1.dist-info/RECORD
beancount_fava-1.2.1.dist-info/WHEEL
beancount_fava-1.2.1.dist-info/entry_points.txt
beancount_fava-1.2.1.dist-info/metadata.json
beancount_fava-1.2.1.dist-info/top_level.txt
fava/__init__.py
fava/application.py
fava/cli.py
fava/json_api.py
fava/template_filters.py
fava/core/__init__.py
fava/core/attributes.py
fava/core/budgets.py
fava/core/charts.py
fava/core/fava_options.py
fava/core/file.py
fava/core/filters.py
fava/core/helpers.py
fava/core/holdings.py
fava/core/misc.py
fava/core/query_shell.py
fava/core/watcher.py
fava/docs/__init__.py
fava/docs/_index.md
fava/docs/beancount_syntax.md
fava/docs/budgets.md
fava/docs/extensions.md
fava/docs/features.md
fava/docs/options.md
fava/docs/running_fava.md
fava/ext/__init__.py
fava/ext/auto_commit.py
fava/plugins/link_statements.py
fava/plugins/tag_discovered_documents.py
fava/static/gen/1eec216b8d6ec331.woff
fava/static/gen/4539170513734535.woff
fava/static/gen/74deac2cc7de3251.woff
fava/static/gen/93464d864471447f.woff
fava/static/gen/a09feb39151c1dbf.woff
fava/static/gen/app.js
fava/static/gen/bca194bb053387f0.woff
fava/static/gen/e3a9f7f43b523838.woff
fava/static/gen/e6c54aa6647996c5.woff
fava/static/gen/style.css
fava/static/images/favicon.ico
fava/templates/_aside.html
fava/templates/_charts.html
fava/templates/_entry_filters.html
fava/templates/_globals.html
fava/templates/_journal_table.html
fava/templates/_layout.html
fava/templates/_query_table.html
fava/templates/_tree_table.html
fava/templates/account.html
fava/templates/balance_sheet.html
fava/templates/commodities.html
fava/templates/context.html
fava/templates/editor.html
fava/templates/errors.html
fava/templates/events.html
fava/templates/help.html
fava/templates/holdings.html
fava/templates/income_statement.html
fava/templates/journal.html
fava/templates/options.html
fava/templates/query.html
fava/templates/statistics.html
fava/templates/trial_balance.html
fava/templates/macros/_account_macros.html
fava/templates/macros/_interval_macros.html
fava/templates/overlays/_documents_upload.html
fava/templates/overlays/_keyboard_shortcuts.html
