Metadata-Version: 2.0
Name: beancount-fava
Version: 1.2.1
Summary: A rich web interface for the CL-accounting tool beancount.
Home-page: https://beancount.github.io/fava/
Author: Dominik Aumayr
Author-email: dominik@aumayr.name
License: MIT
Keywords: fava beancount beancount-fava beancount-webledger ledger-cli cl-accounting
Platform: UNKNOWN
Classifier: Development Status :: 5 - Production/Stable
Classifier: Environment :: Web Environment
Classifier: Framework :: Flask
Classifier: Intended Audience :: Education
Classifier: Intended Audience :: End Users/Desktop
Classifier: Intended Audience :: Financial and Insurance Industry
Classifier: Intended Audience :: Information Technology
Classifier: License :: OSI Approved :: MIT License
Classifier: Natural Language :: English
Classifier: Programming Language :: JavaScript
Classifier: Programming Language :: Python :: 3.5
Classifier: Programming Language :: Python :: 3.6
Classifier: Programming Language :: Python :: 3 :: Only
Classifier: Topic :: Internet :: WWW/HTTP :: Dynamic Content
Classifier: Topic :: Office/Business :: Financial :: Accounting
Classifier: Topic :: Office/Business :: Financial :: Investment
Requires-Dist: Flask (>=0.10.1)
Requires-Dist: Flask-Babel (>=0.10.0)
Requires-Dist: beancount (>=2.0b15)
Requires-Dist: click
Requires-Dist: markdown2 (>=2.3.0)
Requires-Dist: pyreadline; sys_platform == "win32"
Provides-Extra: excel
Requires-Dist: pyexcel (>=0.2.2); extra == 'excel'
Requires-Dist: pyexcel-ods3 (>=0.1.1); extra == 'excel'
Requires-Dist: pyexcel-xls (>=0.1.0); extra == 'excel'
Requires-Dist: pyexcel-xlsx (>=0.1.0); extra == 'excel'
